<annotation>
	<folder>JPEGImages</folder>
	<filename>n02247216_1176.JPEG</filename>
	<path>C:\Users\jhchee\Documents\make_dataset_whiteflies\JPEGImages\n02247216_1176.JPEG</path>
	<source>
		<database>Unknown</database>
	</source>
	<size>
		<width>150</width>
		<height>150</height>
		<depth>3</depth>
	</size>
	<segmented>0</segmented>
	<object>
		<name>whitefly</name>
		<pose>Unspecified</pose>
		<truncated>0</truncated>
		<difficult>0</difficult>
		<bndbox>
			<xmin>31</xmin>
			<ymin>7</ymin>
			<xmax>120</xmax>
			<ymax>142</ymax>
		</bndbox>
	</object>
</annotation>
